gitalong/__info__.py
gitalong/__init__.py
gitalong/batch.py
gitalong/cli.py
gitalong/commit.py
gitalong/contexts.py
gitalong/enums.py
gitalong/exceptions.py
gitalong/functions.py
gitalong/repository.py
gitalong/store.py
gitalong/resources/gitignore
gitalong/resources/hooks/post-applypatch
gitalong/resources/hooks/post-checkout
gitalong/resources/hooks/post-commit
gitalong/resources/hooks/post-rewrite
gitalong/stores/__init__.py
gitalong/stores/git_store.py
gitalong/stores/jsonbin_store.py
gitalong-0.1.0.dev8.dist-info/LICENSE
gitalong-0.1.0.dev8.dist-info/METADATA
gitalong-0.1.0.dev8.dist-info/WHEEL
gitalong-0.1.0.dev8.dist-info/entry_points.txt
gitalong-0.1.0.dev8.dist-info/top_level.txt
gitalong-0.1.0.dev8.dist-info/RECORD
