Metadata-Version: 2.2
Name: gitalong
Version: 0.1.0.dev8
Summary: Git without conflicts.
Home-page: https://github.com/douglaslassance/gitalong-python
Author: Douglas Lassance
Author-email: douglassance@gmail.com
License: MIT
License-File: LICENSE
Requires-Dist: click~=8.1
Requires-Dist: dictdiffer~=0.9
Requires-Dist: gitdb~=4.0
Requires-Dist: GitPython~=3.1
Requires-Dist: requests~=2.31
Provides-Extra: ci
Requires-Dist: black~=24.10; extra == "ci"
Requires-Dist: pep8-naming~=0.13; extra == "ci"
Requires-Dist: Pillow~=10.4; extra == "ci"
Requires-Dist: pylint~=3.0; extra == "ci"
Requires-Dist: pytest-cov~=4.1; extra == "ci"
Requires-Dist: pytest-html~=4.1; extra == "ci"
Requires-Dist: pytest-profiling~=1.7; extra == "ci"
Requires-Dist: responses~=0.24; extra == "ci"
Requires-Dist: setuptools~=69.0; extra == "ci"
Requires-Dist: sphinx-markdown-tables~=0.0; extra == "ci"
Requires-Dist: sphinx-rtd-theme~=2.0; extra == "ci"
Requires-Dist: sphinxcontrib-apidoc~=0.5; extra == "ci"
Requires-Dist: Sphinx~=7.2; extra == "ci"
Requires-Dist: twine~=4.0; extra == "ci"
Requires-Dist: wheel~=0.42; extra == "ci"
Dynamic: author
Dynamic: author-email
Dynamic: description
Dynamic: description-content-type
Dynamic: home-page
Dynamic: license
Dynamic: provides-extra
Dynamic: requires-dist
Dynamic: summary
